saturation/__init__.py
saturation/api.py
saturation/controller.py
saturation/flow.py
saturation/flow_api.py
saturation/main.py
saturation/prediction_api.py
saturation/enJud/__init__.py
saturation/enJud/_init_.py
saturation/enJud/data_process.py
saturation/enJud/fenleipanbie.py
saturation/enJud/huo_canshu.py
saturation/enJud/julei.py
saturation/enJud/main.py
saturation/enJud/panbie.py
saturation/enJud/yuzhi.py
saturation/pre/__init__.py
saturation/pre/_init_.py
saturation/pre/model_all.h5
saturation/pre/model_huo.h5
saturation/pre/model_huo1.h5
saturation/pre/model_ke.h5
saturation/pre/model_ke1.h5
saturation/pre/预测模型.py
saturation/satAna/__init__.py
saturation/satAna/_init_.py
saturation/satAna/saturation.py
saturation/utils/__init__.py
saturation/utils/config.py
saturation/utils/file_utils.py
saturation-1.1.0.dist-info/METADATA
saturation-1.1.0.dist-info/WHEEL
saturation-1.1.0.dist-info/entry_points.txt
saturation-1.1.0.dist-info/top_level.txt
saturation-1.1.0.dist-info/RECORD
