Metadata-Version: 2.4
Name: saturation
Version: 1.1.0
Summary: 服务区饱和度分析系统
Home-page: 
Author: 应用团队
Keywords: traffic analysis,saturation,prediction,machine learning
Classifier: Development Status :: 5 - Production/Stable
Classifier: Intended Audience :: Science/Research
Classifier: Intended Audience :: Developers
Classifier: License :: OSI Approved :: MIT License
Classifier: Programming Language :: Python :: 3
Classifier: Programming Language :: Python :: 3.7
Classifier: Programming Language :: Python :: 3.8
Classifier: Programming Language :: Python :: 3.9
Classifier: Topic :: Scientific/Engineering
Classifier: Topic :: Scientific/Engineering :: Information Analysis
Requires-Python: >=3.7
Requires-Dist: pandas>=1.0.0
Requires-Dist: numpy>=1.18.0
Requires-Dist: scikit-learn>=0.22.0
Requires-Dist: matplotlib>=3.1.0
Requires-Dist: tensorflow>=2.0.0
Requires-Dist: keras>=2.3.0
Requires-Dist: scipy>=1.4.0
Requires-Dist: scikit-fuzzy>=0.4.2
Requires-Dist: packaging>=20.0
Requires-Dist: scikit-opt>=0.6.0
Dynamic: author
Dynamic: classifier
Dynamic: description
Dynamic: description-content-type
Dynamic: keywords
Dynamic: requires-dist
Dynamic: requires-python
Dynamic: summary
